CHANGES.rst
MANIFEST.in
README.rst
setup.cfg
setup.py
socketIO_client/__init__.py
socketIO_client/exceptions.py
socketIO_client/heartbeats.py
socketIO_client/logs.py
socketIO_client/namespaces.py
socketIO_client/parsers.py
socketIO_client/symmetries.py
socketIO_client/transports.py
socketIO_client/tests/__init__.py
socketIO_client/tests/index.html
socketIO_client/tests/package.json
socketIO_client/tests/proxy.js
socketIO_client/tests/serve.js
socketIO_client/tests/ssl.crt
socketIO_client/tests/ssl.key
socketIO_client_2.egg-info/PKG-INFO
socketIO_client_2.egg-info/SOURCES.txt
socketIO_client_2.egg-info/dependency_links.txt
socketIO_client_2.egg-info/not-zip-safe
socketIO_client_2.egg-info/pbr.json
socketIO_client_2.egg-info/requires.txt
socketIO_client_2.egg-info/top_level.txt