Metadata-Version: 1.1
Name: socketIO-client-2
Version: 0.7.0
Summary: A socket.io client library
Home-page: https://github.com/feus4177/socketIO-client-2
Author: John Feusi
Author-email: feus4177@gmail.com
License: MIT
Keywords: socket.io node.js
Platform: UNKNOWN
Classifier: Intended Audience :: Developers
Classifier: Programming Language :: Python
Classifier: License :: OSI Approved :: MIT License
Classifier: Development Status :: 5 - Production/Stable
